uac_api/__init__.py
uac_api/agents.py
uac_api/audits.py
uac_api/bundles.py
uac_api/business_services.py
uac_api/calendars.py
uac_api/cluster_nodes.py
uac_api/connections.py
uac_api/credentials.py
uac_api/custom_days.py
uac_api/email_templates.py
uac_api/ldap.py
uac_api/metrics.py
uac_api/oauth_clients.py
uac_api/oms_servers.py
uac_api/payload.py
uac_api/properties.py
uac_api/reports.py
uac_api/scripts.py
uac_api/server_operations.py
uac_api/simulations.py
uac_api/system.py
uac_api/task_instances.py
uac_api/tasks.py
uac_api/triggers.py
uac_api/universal_event_templates.py
uac_api/universal_events.py
uac_api/universal_templates.py
uac_api/user_groups.py
uac_api/users.py
uac_api/utils.py
uac_api/utils_workflow.py
uac_api/variables.py
uac_api/virtual_resources.py
uac_api/webhooks.py
uac_api/workflows.py
uac_api-0.4.14.dist-info/METADATA
uac_api-0.4.14.dist-info/WHEEL
uac_api-0.4.14.dist-info/top_level.txt
uac_api-0.4.14.dist-info/RECORD
