Metadata-Version: 2.1
Name: uac-api
Version: 0.4.14
Summary: A Python wrapper for the Stonebranch UAC API
Home-page: https://github.com/gomleksiz/uac-api
Author: Stonebranch
Author-email: huseyim@gmail.com
License: CC BY-NC 4.0
Classifier: Programming Language :: Python :: 3
Classifier: License :: OSI Approved :: MIT License
Classifier: Operating System :: OS Independent
Requires-Python: >=3.7
Requires-Dist: requests
Provides-Extra: networkx
Requires-Dist: networkx ; extra == 'networkx'
